AUTHORS
LICENSE
MANIFEST.in
README.rst
setup.py
alignak_checks_EXAMPLE/__init__.py
alignak_checks_EXAMPLE/commands.cfg
alignak_checks_EXAMPLE/services.cfg
alignak_checks_EXAMPLE/templates.cfg
alignak_checks_EXAMPLE.egg-info/PKG-INFO
alignak_checks_EXAMPLE.egg-info/SOURCES.txt
alignak_checks_EXAMPLE.egg-info/dependency_links.txt
alignak_checks_EXAMPLE.egg-info/not-zip-safe
alignak_checks_EXAMPLE.egg-info/top_level.txt
alignak_checks_EXAMPLE/plugins/checkexample.py