Metadata-Version: 1.1
Name: alignak-checks-EXAMPLE
Version: 0.2.2
Summary: Alignak - Example and how-to build a checks pack for Alignak monitoring framework.
Home-page: https://github.com/Alignak-monitoring-contrib/alignak-checks-example
Author: Frédéric MOHIER
Author-email: frederic.mohier@gmail.com
License: GNU Affero General Public License, version 3
Keywords: alignak monitoring pack checks EXAMPLE
Platform: UNKNOWN
Classifier: Development Status :: 4 - Beta
Classifier: Environment :: Console
Classifier: Intended Audience :: Developers
Classifier: Intended Audience :: System Administrators
Classifier: License :: OSI Approved :: GNU General Public License v3 (GPLv3)
Classifier: Natural Language :: English
Classifier: Programming Language :: Python
Classifier: Topic :: System :: Monitoring
Classifier: Topic :: System :: Systems Administration
